{
  "platform": "ios",
  "analysisType": "dynamic",
  "stages": [
    {
      "id": "interactive-analysis",
      "order": 1,
      "execution": "parallel",
      "runPolicy": "on-success",
      "tasks": [
        {
          "taskType": "ios-dynamic-session",
          "workerType": "ios-dynamic-analysis",
          "tool": "frida",
          "order": 1,
          "parameters": {
            "bundleId": "com.example.app",
            "sessionTimeoutSeconds": 30,
            "scriptProfile": "ios-basic",
            "enabledScripts": [],
            "disabledScripts": []
          }
        }
      ]
    }
  ]
}
